asyauth/__init__.py
asyauth/_version.py
asyauth/common/__init__.py
asyauth/common/clientauthalgo.py
asyauth/common/constants.py
asyauth/common/credentials/__init__.py
asyauth/common/credentials/credssp.py
asyauth/common/credentials/kerberos.py
asyauth/common/credentials/ntlm.py
asyauth/common/credentials/spnego.py
asyauth/common/credentials/spnegoex.py
asyauth/common/subprotocols/__init__.py
asyauth/common/subprotocols/custom.py
asyauth/common/subprotocols/native.py
asyauth/common/subprotocols/sspi.py
asyauth/common/subprotocols/sspiproxy.py
asyauth/common/subprotocols/wsnet.py
asyauth/common/subprotocols/wsnetdirect.py
asyauth/common/winapi/__init__.py
asyauth/common/winapi/constants.py
asyauth/common/winapi/functiondefs.py
asyauth/common/winapi/token.py
asyauth/common/winapi/winsspi.py
asyauth/protocols/__init__.py
asyauth/protocols/credssp/__init__.py
asyauth/protocols/credssp/client/__init__.py
asyauth/protocols/credssp/client/native.py
asyauth/protocols/credssp/messages/__init__.py
asyauth/protocols/credssp/messages/asn1_structs.py
asyauth/protocols/credssp/messages/remcredguard.py
asyauth/protocols/kerberos/__init__.py
asyauth/protocols/kerberos/gssapi.py
asyauth/protocols/kerberos/gssapismb.py
asyauth/protocols/kerberos/client/__init__.py
asyauth/protocols/kerberos/client/native.py
asyauth/protocols/kerberos/client/sspi.py
asyauth/protocols/kerberos/client/sspiproxy.py
asyauth/protocols/kerberos/client/wsnet.py
asyauth/protocols/kerberos/client/wsnetdirect.py
asyauth/protocols/ntlm/__init__.py
asyauth/protocols/ntlm/creds_calc.py
asyauth/protocols/ntlm/client/__init__.py
asyauth/protocols/ntlm/client/native.py
asyauth/protocols/ntlm/client/sspi.py
asyauth/protocols/ntlm/client/sspiproxy.py
asyauth/protocols/ntlm/client/wsnet.py
asyauth/protocols/ntlm/client/wsnetdirect.py
asyauth/protocols/ntlm/messages/__init__.py
asyauth/protocols/ntlm/messages/authenticate.py
asyauth/protocols/ntlm/messages/challenge.py
asyauth/protocols/ntlm/messages/negotiate.py
asyauth-0.0.22.dist-info/LICENSE
asyauth-0.0.22.dist-info/METADATA
asyauth-0.0.22.dist-info/WHEEL
asyauth-0.0.22.dist-info/top_level.txt
asyauth-0.0.22.dist-info/RECORD
